pypackage_info/__init__.py
pypackage_info/__main__.py
pypackage_info/info.py
pypackage_info-0.0.2.dist-info/LICENSE
pypackage_info-0.0.2.dist-info/METADATA
pypackage_info-0.0.2.dist-info/WHEEL
pypackage_info-0.0.2.dist-info/entry_points.txt
pypackage_info-0.0.2.dist-info/top_level.txt
pypackage_info-0.0.2.dist-info/RECORD
